{"flowContents":{"identifier":"50e89c1a-0aad-32ee-96ce-08f118f282ce","instanceIdentifier":"7bf81475-0184-1000-3584-0b474369c1a4","name":"iow_LDES_timescale (4)","comments":"","position":{"x":1048.0,"y":266.0},"processGroups":[],"remoteProcessGroups":[],"processors":[{"identifier":"d4649661-514d-3101-801d-2bf66f1c759d","instanceIdentifier":"fabbe3f1-cb19-3762-df31-6fe4d91052b2","name":"JSON to SQL","comments":"","position":{"x":1648.0,"y":280.0},"type":"org.apache.nifi.processors.standard.ConvertJSONToSQL","bundle":{"group":"org.apache.nifi","artifact":"nifi-standard-nar","version":"1.17.0"},"properties":{"table-schema-cache-size":"100","Table Name":"water_quality","Catalog Name":null,"jts-sql-param-attr-prefix":"sql","Schema Name":null,"Unmatched Field Behavior":"Ignore Unmatched Fields","Unmatched Column Behavior":"Ignore Unmatched Columns","jts-quoted-identifiers":"true","jts-quoted-table-identifiers":"false","JDBC Connection Pool":"8701abec-7829-3012-bcd3-d10972420545","Update Keys":null,"Translate Field Names":"true","Statement Type":"INSERT"},"propertyDescriptors":{"table-schema-cache-size":{"name":"table-schema-cache-size","displayName":"Table Schema Cache Size","identifiesControllerService":false,"sensitive":false},"Table Name":{"name":"Table Name","displayName":"Table Name","identifiesControllerService":false,"sensitive":false},"Catalog Name":{"name":"Catalog Name","displayName":"Catalog Name","identifiesControllerService":false,"sensitive":false},"jts-sql-param-attr-prefix":{"name":"jts-sql-param-attr-prefix","displayName":"SQL Parameter Attribute Prefix","identifiesControllerService":false,"sensitive":false},"Schema Name":{"name":"Schema Name","displayName":"Schema Name","identifiesControllerService":false,"sensitive":false},"Unmatched Field Behavior":{"name":"Unmatched Field Behavior","displayName":"Unmatched Field Behavior","identifiesControllerService":false,"sensitive":false},"Unmatched Column Behavior":{"name":"Unmatched Column Behavior","displayName":"Unmatched Column Behavior","identifiesControllerService":false,"sensitive":false},"jts-quoted-identifiers":{"name":"jts-quoted-identifiers","displayName":"Quote Column Identifiers","identifiesControllerService":false,"sensitive":false},"jts-quoted-table-identifiers":{"name":"jts-quoted-table-identifiers","displayName":"Quote Table Identifiers","identifiesControllerService":false,"sensitive":false},"JDBC Connection Pool":{"name":"JDBC Connection Pool","displayName":"JDBC Connection Pool","identifiesControllerService":true,"sensitive":false},"Update Keys":{"name":"Update Keys","displayName":"Update Keys","identifiesControllerService":false,"sensitive":false},"Translate Field Names":{"name":"Translate Field Names","displayName":"Translate Field Names","identifiesControllerService":false,"sensitive":false},"Statement Type":{"name":"Statement Type","displayName":"Statement Type","identifiesControllerService":false,"sensitive":false}},"style":{},"schedulingPeriod":"0 sec","schedulingStrategy":"TIMER_DRIVEN","executionNode":"ALL","penaltyDuration":"30 sec","yieldDuration":"1 sec","bulletinLevel":"WARN","runDurationMillis":0,"concurrentlySchedulableTaskCount":1,"autoTerminatedRelationships":["original","failure"],"scheduledState":"ENABLED","retryCount":10,"retriedRelationships":[],"backoffMechanism":"PENALIZE_FLOWFILE","maxBackoffPeriod":"10 mins","componentType":"PROCESSOR","groupIdentifier":"50e89c1a-0aad-32ee-96ce-08f118f282ce"},{"identifier":"be454341-6b9c-372e-a4bb-b08fb3de1b14","instanceIdentifier":"c2031048-deb5-3952-6ddd-b4e94025158b","name":"IOW LdesClient","comments":"","position":{"x":408.0,"y":-8.0},"type":"be.vlaanderen.informatievlaanderen.ldes.processors.LdesClient","bundle":{"group":"be.vlaanderen.informatievlaanderen","artifact":"ldes-client-processor","version":"1.0-SNAPSHOT"},"properties":{"FRAGMENT_EXPIRATION_INTERVAL":"30","DATA_SOURCE_FORMAT":"TURTLE","DATA_DESTINATION_FORMAT":"n-quads","DATA_SOURCE_URL":"https://iow.smartdataspace.beta-vlaanderen.be/water-quality-observations-timebased"},"propertyDescriptors":{"FRAGMENT_EXPIRATION_INTERVAL":{"name":"FRAGMENT_EXPIRATION_INTERVAL","displayName":"Fragment expiration interval","identifiesControllerService":false,"sensitive":false},"DATA_SOURCE_FORMAT":{"name":"DATA_SOURCE_FORMAT","displayName":"Data source format","identifiesControllerService":false,"sensitive":false},"DATA_DESTINATION_FORMAT":{"name":"DATA_DESTINATION_FORMAT","displayName":"Data destination format","identifiesControllerService":false,"sensitive":false},"DATA_SOURCE_URL":{"name":"DATA_SOURCE_URL","displayName":"Data source url","identifiesControllerService":false,"sensitive":false}},"style":{},"schedulingPeriod":"0 sec","schedulingStrategy":"TIMER_DRIVEN","executionNode":"ALL","penaltyDuration":"30 sec","yieldDuration":"1 sec","bulletinLevel":"WARN","runDurationMillis":0,"concurrentlySchedulableTaskCount":1,"autoTerminatedRelationships":[],"scheduledState":"ENABLED","retryCount":10,"retriedRelationships":[],"backoffMechanism":"PENALIZE_FLOWFILE","maxBackoffPeriod":"10 mins","componentType":"PROCESSOR","groupIdentifier":"50e89c1a-0aad-32ee-96ce-08f118f282ce"},{"identifier":"bce23fb0-ba67-3898-b8a4-65e1ce2acd65","instanceIdentifier":"683abdc2-2bb7-3f6c-63ae-e5d38b79baea","name":"upsert in PostgreSQL","comments":"","position":{"x":1032.0,"y":528.0},"type":"org.apache.nifi.processors.standard.ExecuteSQL","bundle":{"group":"org.apache.nifi","artifact":"nifi-standard-nar","version":"1.17.0"},"properties":{"esql-max-rows":"0","dbf-default-precision":"10","Max Wait Time":"0 seconds","Database Connection Pooling Service":"8701abec-7829-3012-bcd3-d10972420545","sql-post-query":null,"esql-auto-commit":"true","dbf-user-logical-types":"false","dbf-default-scale":"0","sql-pre-query":"DELETE FROM water_quality WHERE \"id\" = '${sql.args.1.value}';","compression-format":"NONE","esql-output-batch-size":"0","esql-fetch-size":"0","SQL select query":null,"dbf-normalize":"false"},"propertyDescriptors":{"esql-max-rows":{"name":"esql-max-rows","displayName":"Max Rows Per Flow File","identifiesControllerService":false,"sensitive":false},"dbf-default-precision":{"name":"dbf-default-precision","displayName":"Default Decimal Precision","identifiesControllerService":false,"sensitive":false},"Max Wait Time":{"name":"Max Wait Time","displayName":"Max Wait Time","identifiesControllerService":false,"sensitive":false},"Database Connection Pooling Service":{"name":"Database Connection Pooling Service","displayName":"Database Connection Pooling Service","identifiesControllerService":true,"sensitive":false},"sql-post-query":{"name":"sql-post-query","displayName":"SQL Post-Query","identifiesControllerService":false,"sensitive":false},"esql-auto-commit":{"name":"esql-auto-commit","displayName":"Set Auto Commit","identifiesControllerService":false,"sensitive":false},"dbf-user-logical-types":{"name":"dbf-user-logical-types","displayName":"Use Avro Logical Types","identifiesControllerService":false,"sensitive":false},"dbf-default-scale":{"name":"dbf-default-scale","displayName":"Default Decimal Scale","identifiesControllerService":false,"sensitive":false},"sql-pre-query":{"name":"sql-pre-query","displayName":"SQL Pre-Query","identifiesControllerService":false,"sensitive":false},"compression-format":{"name":"compression-format","displayName":"Compression Format","identifiesControllerService":false,"sensitive":false},"esql-output-batch-size":{"name":"esql-output-batch-size","displayName":"Output Batch Size","identifiesControllerService":false,"sensitive":false},"esql-fetch-size":{"name":"esql-fetch-size","displayName":"Fetch Size","identifiesControllerService":false,"sensitive":false},"SQL select query":{"name":"SQL select query","displayName":"SQL select query","identifiesControllerService":false,"sensitive":false},"dbf-normalize":{"name":"dbf-normalize","displayName":"Normalize Table/Column Names","identifiesControllerService":false,"sensitive":false}},"style":{},"schedulingPeriod":"0 sec","schedulingStrategy":"TIMER_DRIVEN","executionNode":"ALL","penaltyDuration":"30 sec","yieldDuration":"1 sec","bulletinLevel":"WARN","runDurationMillis":0,"concurrentlySchedulableTaskCount":1,"autoTerminatedRelationships":["success","failure"],"scheduledState":"ENABLED","retryCount":10,"retriedRelationships":[],"backoffMechanism":"PENALIZE_FLOWFILE","maxBackoffPeriod":"10 mins","componentType":"PROCESSOR","groupIdentifier":"50e89c1a-0aad-32ee-96ce-08f118f282ce"},{"identifier":"6738a1c8-1603-335f-a48b-7782c4a999a8","instanceIdentifier":"4b8c3c27-6c00-3617-999c-29c0bb453f61","name":"Nquads to JSON-LD","comments":"","position":{"x":408.0,"y":272.0},"type":"be.vlaanderen.informatievlaanderen.processors.RDFSerialisationProcessor","bundle":{"group":"be.vlaanderen.informatievlaanderen","artifact":"nifi-rdf-serialisation-processors","version":"0.2-Special-Samuel-Edition"},"properties":{"SOURCE_SERIALISATION":"N-Quads","TARGET_SERIALISATION":"JSON-LD","CONTEXT_URI":"https://data.vlaanderen.be/doc/applicatieprofiel/waterkwaliteit/ontwerpstandaard/2022-05-24/context/waterkwaliteit-ap.jsonld"},"propertyDescriptors":{"SOURCE_SERIALISATION":{"name":"SOURCE_SERIALISATION","displayName":"Serialisation of the incoming FlowFile.","identifiesControllerService":false,"sensitive":false},"TARGET_SERIALISATION":{"name":"TARGET_SERIALISATION","displayName":"Serialisation of the outgoing FlowFile.","identifiesControllerService":false,"sensitive":false},"CONTEXT_URI":{"name":"CONTEXT_URI","displayName":"The JSON-LD context to apply.","identifiesControllerService":false,"sensitive":false}},"style":{},"schedulingPeriod":"0 sec","schedulingStrategy":"TIMER_DRIVEN","executionNode":"ALL","penaltyDuration":"30 sec","yieldDuration":"1 sec","bulletinLevel":"WARN","runDurationMillis":0,"concurrentlySchedulableTaskCount":1,"autoTerminatedRelationships":["FAILURE"],"scheduledState":"ENABLED","retryCount":10,"retriedRelationships":[],"backoffMechanism":"PENALIZE_FLOWFILE","maxBackoffPeriod":"10 mins","componentType":"PROCESSOR","groupIdentifier":"50e89c1a-0aad-32ee-96ce-08f118f282ce"},{"identifier":"de3d08fa-81d7-333c-9b75-c28b68088e9f","instanceIdentifier":"ae4848fc-0a88-31a3-1bac-88be307d06c6","name":"VersionMaterialiseProcessor","comments":"","position":{"x":1128.0,"y":-24.0},"type":"be.vlaanderen.informatievlaanderen.processors.VersionMaterialiseProcessor","bundle":{"group":"be.vlaanderen.informatievlaanderen","artifact":"nifi-ldes-version-materialisation-processors","version":"0.3-SNAPSHOT"},"properties":{"MembersOnly":"false","isVersionOf":"http://purl.org/dc/terms/isVersionOf"},"propertyDescriptors":{"MembersOnly":{"name":"MembersOnly","displayName":"Restrict output to members","identifiesControllerService":false,"sensitive":false},"isVersionOf":{"name":"isVersionOf","displayName":"Predicate used for isVersionOf","identifiesControllerService":false,"sensitive":false}},"style":{},"schedulingPeriod":"0 sec","schedulingStrategy":"TIMER_DRIVEN","executionNode":"ALL","penaltyDuration":"30 sec","yieldDuration":"1 sec","bulletinLevel":"WARN","runDurationMillis":0,"concurrentlySchedulableTaskCount":1,"autoTerminatedRelationships":["Failure"],"scheduledState":"ENABLED","retryCount":10,"retriedRelationships":[],"backoffMechanism":"PENALIZE_FLOWFILE","maxBackoffPeriod":"10 mins","componentType":"PROCESSOR","groupIdentifier":"50e89c1a-0aad-32ee-96ce-08f118f282ce"},{"identifier":"dd9cc19c-b402-329c-a298-09415f97bf8d","instanceIdentifier":"cc6b493d-78ae-3013-bb20-c0c98fa6b48b","name":"Flatten JSON to key-value pairs","comments":"","position":{"x":1032.0,"y":272.0},"type":"org.apache.nifi.processors.standard.JoltTransformJSON","bundle":{"group":"org.apache.nifi","artifact":"nifi-standard-nar","version":"1.17.0"},"properties":{"jolt-spec":"[\n  {\n    \"operation\": \"shift\",\n    \"spec\": {\n      \"*id\": \"id\",\n      \"Bemonsteringsobjectverzameling.lid\": {\n        \"*\": {\n          \"Observatie:.phenomenonTime\": {\n            \"*value\": \"&(2,0).date\"\n          },\n          \"Observatie.uitgevoerdMetSensor\": \"&(1,0).sensor\",\n          \"Observatie.geobserveerdKenmerk\": \"&(1,0).kenmerk\",\n          \"Observatie.resultaat\": {\n            \"Maat.maat\": {\n              \"https://schema.org/value\": {\n                \"*value\": \"&(4,0).value\"\n              }\n            }\n          }\n        }\n      }\n    }\n  },\n  {\n    \"operation\": \"shift\",\n    \"spec\": {\n      \"id\": \"id\",\n      \"*\": {\n        \"value\": \"@(1,kenmerk).value\",\n        \"date\": \"@(1,kenmerk).date\",\n        \"sensor\": \"@(1,kenmerk).sensor\"\n      }\n    }\n  },\n  {\n    \"operation\": \"shift\",\n    \"spec\": {\n      \"id\": \"id\",\n      \"https://data.vmm.be/concept/sensor/batterijniveau\": \"batterijniveau\",\n      \"https://data.vmm.be/concept/waterkwaliteitparameter/temperatuur\": \"temperatuur\",\n      \"https://data.vmm.be/concept/waterkwaliteitparameter/conductiviteit\": \"conductiviteit\"\n    }\n  },\n  {\n    \"operation\": \"shift\",\n    \"spec\": {\n      \"id\": \"id\",\n      \"*\": {\n        \"*\": \"&1_&0\"\n      }\n    }\n  }\n]","jolt-transform":"jolt-transform-chain","jolt-custom-class":null,"jolt-custom-modules":null,"pretty_print":"false","Transform Cache Size":"1"},"propertyDescriptors":{"jolt-spec":{"name":"jolt-spec","displayName":"Jolt Specification","identifiesControllerService":false,"sensitive":false},"jolt-transform":{"name":"jolt-transform","displayName":"Jolt Transformation DSL","identifiesControllerService":false,"sensitive":false},"jolt-custom-class":{"name":"jolt-custom-class","displayName":"Custom Transformation Class Name","identifiesControllerService":false,"sensitive":false},"jolt-custom-modules":{"name":"jolt-custom-modules","displayName":"Custom Module Directory","identifiesControllerService":false,"sensitive":false,"resourceDefinition":{"cardinality":"MULTIPLE","resourceTypes":["DIRECTORY","FILE"]}},"pretty_print":{"name":"pretty_print","displayName":"Pretty Print","identifiesControllerService":false,"sensitive":false},"Transform Cache Size":{"name":"Transform Cache Size","displayName":"Transform Cache Size","identifiesControllerService":false,"sensitive":false}},"style":{},"schedulingPeriod":"0 sec","schedulingStrategy":"TIMER_DRIVEN","executionNode":"ALL","penaltyDuration":"30 sec","yieldDuration":"1 sec","bulletinLevel":"WARN","runDurationMillis":0,"concurrentlySchedulableTaskCount":1,"autoTerminatedRelationships":["failure"],"scheduledState":"ENABLED","retryCount":10,"retriedRelationships":[],"backoffMechanism":"PENALIZE_FLOWFILE","maxBackoffPeriod":"10 mins","componentType":"PROCESSOR","groupIdentifier":"50e89c1a-0aad-32ee-96ce-08f118f282ce"}],"inputPorts":[],"outputPorts":[],"connections":[{"identifier":"5bc5901f-5acd-3873-8d80-d7037286e978","instanceIdentifier":"19f8b9b5-e07f-38d8-46b4-738a80478786","name":"","source":{"id":"d4649661-514d-3101-801d-2bf66f1c759d","type":"PROCESSOR","groupId":"50e89c1a-0aad-32ee-96ce-08f118f282ce","name":"JSON to SQL","comments":"","instanceIdentifier":"fabbe3f1-cb19-3762-df31-6fe4d91052b2"},"destination":{"id":"bce23fb0-ba67-3898-b8a4-65e1ce2acd65","type":"PROCESSOR","groupId":"50e89c1a-0aad-32ee-96ce-08f118f282ce","name":"upsert in PostgreSQL","comments":"","instanceIdentifier":"683abdc2-2bb7-3f6c-63ae-e5d38b79baea"},"labelIndex":1,"zIndex":0,"selectedRelationships":["sql"],"backPressureObjectThreshold":10000,"backPressureDataSizeThreshold":"1 GB","flowFileExpiration":"0 sec","prioritizers":[],"bends":[],"loadBalanceStrategy":"DO_NOT_LOAD_BALANCE","partitioningAttribute":"","loadBalanceCompression":"DO_NOT_COMPRESS","componentType":"CONNECTION","groupIdentifier":"50e89c1a-0aad-32ee-96ce-08f118f282ce"},{"identifier":"3075642d-1d70-3ccd-b8f5-ed9fed104ade","instanceIdentifier":"ee2ecf90-4690-3844-8aa3-2c6ba7a5c700","name":"","source":{"id":"dd9cc19c-b402-329c-a298-09415f97bf8d","type":"PROCESSOR","groupId":"50e89c1a-0aad-32ee-96ce-08f118f282ce","name":"Flatten JSON to key-value pairs","comments":"","instanceIdentifier":"cc6b493d-78ae-3013-bb20-c0c98fa6b48b"},"destination":{"id":"d4649661-514d-3101-801d-2bf66f1c759d","type":"PROCESSOR","groupId":"50e89c1a-0aad-32ee-96ce-08f118f282ce","name":"JSON to SQL","comments":"","instanceIdentifier":"fabbe3f1-cb19-3762-df31-6fe4d91052b2"},"labelIndex":1,"zIndex":0,"selectedRelationships":["success"],"backPressureObjectThreshold":10000,"backPressureDataSizeThreshold":"1 GB","flowFileExpiration":"0 sec","prioritizers":[],"bends":[],"loadBalanceStrategy":"DO_NOT_LOAD_BALANCE","partitioningAttribute":"","loadBalanceCompression":"DO_NOT_COMPRESS","componentType":"CONNECTION","groupIdentifier":"50e89c1a-0aad-32ee-96ce-08f118f282ce"},{"identifier":"2dfef8b4-d1a6-32fd-9f25-567fd5158dfb","instanceIdentifier":"6e3f2293-a91d-3048-7dae-515b542fdd2d","name":"","source":{"id":"6738a1c8-1603-335f-a48b-7782c4a999a8","type":"PROCESSOR","groupId":"50e89c1a-0aad-32ee-96ce-08f118f282ce","name":"Nquads to JSON-LD","comments":"","instanceIdentifier":"4b8c3c27-6c00-3617-999c-29c0bb453f61"},"destination":{"id":"dd9cc19c-b402-329c-a298-09415f97bf8d","type":"PROCESSOR","groupId":"50e89c1a-0aad-32ee-96ce-08f118f282ce","name":"Flatten JSON to key-value pairs","comments":"","instanceIdentifier":"cc6b493d-78ae-3013-bb20-c0c98fa6b48b"},"labelIndex":1,"zIndex":0,"selectedRelationships":["SUCCESS"],"backPressureObjectThreshold":10000,"backPressureDataSizeThreshold":"1 GB","flowFileExpiration":"0 sec","prioritizers":[],"bends":[],"loadBalanceStrategy":"DO_NOT_LOAD_BALANCE","partitioningAttribute":"","loadBalanceCompression":"DO_NOT_COMPRESS","componentType":"CONNECTION","groupIdentifier":"50e89c1a-0aad-32ee-96ce-08f118f282ce"},{"identifier":"d7a41ade-ed77-3136-b88f-4d290f0efa83","instanceIdentifier":"46d57129-1721-347f-d3cf-60a30836538b","name":"VersionMater","source":{"id":"de3d08fa-81d7-333c-9b75-c28b68088e9f","type":"PROCESSOR","groupId":"50e89c1a-0aad-32ee-96ce-08f118f282ce","name":"VersionMaterialiseProcessor","comments":"","instanceIdentifier":"ae4848fc-0a88-31a3-1bac-88be307d06c6"},"destination":{"id":"6738a1c8-1603-335f-a48b-7782c4a999a8","type":"PROCESSOR","groupId":"50e89c1a-0aad-32ee-96ce-08f118f282ce","name":"Nquads to JSON-LD","comments":"","instanceIdentifier":"4b8c3c27-6c00-3617-999c-29c0bb453f61"},"labelIndex":1,"zIndex":0,"selectedRelationships":["Success"],"backPressureObjectThreshold":10000,"backPressureDataSizeThreshold":"1 GB","flowFileExpiration":"0 sec","prioritizers":[],"bends":[],"loadBalanceStrategy":"DO_NOT_LOAD_BALANCE","partitioningAttribute":"","loadBalanceCompression":"DO_NOT_COMPRESS","componentType":"CONNECTION","groupIdentifier":"50e89c1a-0aad-32ee-96ce-08f118f282ce"},{"identifier":"2847a01c-d49c-3c73-9862-1a0eb2a51454","instanceIdentifier":"f93677e1-666d-3817-06c2-347b674418da","name":"","source":{"id":"be454341-6b9c-372e-a4bb-b08fb3de1b14","type":"PROCESSOR","groupId":"50e89c1a-0aad-32ee-96ce-08f118f282ce","name":"IOW LdesClient","comments":"","instanceIdentifier":"c2031048-deb5-3952-6ddd-b4e94025158b"},"destination":{"id":"de3d08fa-81d7-333c-9b75-c28b68088e9f","type":"PROCESSOR","groupId":"50e89c1a-0aad-32ee-96ce-08f118f282ce","name":"VersionMaterialiseProcessor","comments":"","instanceIdentifier":"ae4848fc-0a88-31a3-1bac-88be307d06c6"},"labelIndex":1,"zIndex":0,"selectedRelationships":["data"],"backPressureObjectThreshold":10000,"backPressureDataSizeThreshold":"1 GB","flowFileExpiration":"0 sec","prioritizers":[],"bends":[],"loadBalanceStrategy":"DO_NOT_LOAD_BALANCE","partitioningAttribute":"","loadBalanceCompression":"DO_NOT_COMPRESS","componentType":"CONNECTION","groupIdentifier":"50e89c1a-0aad-32ee-96ce-08f118f282ce"}],"labels":[],"funnels":[],"controllerServices":[{"identifier":"8701abec-7829-3012-bcd3-d10972420545","instanceIdentifier":"11f9a2af-a04e-32f5-4019-0b40d8cacf09","name":"DBCPConnectionPool","comments":"","type":"org.apache.nifi.dbcp.DBCPConnectionPool","bundle":{"group":"org.apache.nifi","artifact":"nifi-dbcp-service-nar","version":"1.17.0"},"properties":{"dbcp-min-idle-conns":"0","Max Wait Time":"500 millis","Database Driver Class Name":"org.postgresql.Driver","dbcp-min-evictable-idle-time":"30 mins","kerberos-principal":null,"Max Total Connections":"8","kerberos-credentials-service":null,"dbcp-max-conn-lifetime":"-1","Validation-query":"select 1","Database Connection URL":"jdbc:postgresql://ldes-postgis/water_quality","dbcp-time-between-eviction-runs":"-1","Database User":"postgres","kerberos-user-service":null,"dbcp-soft-min-evictable-idle-time":"-1","database-driver-locations":"/opt/nifi/nifi-current/extensions/postgresql-42.5.0.jar","dbcp-max-idle-conns":"8"},"propertyDescriptors":{"kerberos-password":{"name":"kerberos-password","displayName":"Kerberos Password","identifiesControllerService":false,"sensitive":true},"dbcp-min-idle-conns":{"name":"dbcp-min-idle-conns","displayName":"Minimum Idle Connections","identifiesControllerService":false,"sensitive":false},"Max Wait Time":{"name":"Max Wait Time","displayName":"Max Wait Time","identifiesControllerService":false,"sensitive":false},"Database Driver Class Name":{"name":"Database Driver Class Name","displayName":"Database Driver Class Name","identifiesControllerService":false,"sensitive":false},"dbcp-min-evictable-idle-time":{"name":"dbcp-min-evictable-idle-time","displayName":"Minimum Evictable Idle Time","identifiesControllerService":false,"sensitive":false},"kerberos-principal":{"name":"kerberos-principal","displayName":"Kerberos Principal","identifiesControllerService":false,"sensitive":false},"Max Total Connections":{"name":"Max Total Connections","displayName":"Max Total Connections","identifiesControllerService":false,"sensitive":false},"kerberos-credentials-service":{"name":"kerberos-credentials-service","displayName":"Kerberos Credentials Service","identifiesControllerService":true,"sensitive":false},"dbcp-max-conn-lifetime":{"name":"dbcp-max-conn-lifetime","displayName":"Max Connection Lifetime","identifiesControllerService":false,"sensitive":false},"Validation-query":{"name":"Validation-query","displayName":"Validation query","identifiesControllerService":false,"sensitive":false},"Database Connection URL":{"name":"Database Connection URL","displayName":"Database Connection URL","identifiesControllerService":false,"sensitive":false},"dbcp-time-between-eviction-runs":{"name":"dbcp-time-between-eviction-runs","displayName":"Time Between Eviction Runs","identifiesControllerService":false,"sensitive":false},"Database User":{"name":"Database User","displayName":"Database User","identifiesControllerService":false,"sensitive":false},"kerberos-user-service":{"name":"kerberos-user-service","displayName":"Kerberos User Service","identifiesControllerService":true,"sensitive":false},"dbcp-soft-min-evictable-idle-time":{"name":"dbcp-soft-min-evictable-idle-time","displayName":"Soft Minimum Evictable Idle Time","identifiesControllerService":false,"sensitive":false},"database-driver-locations":{"name":"database-driver-locations","displayName":"Database Driver Location(s)","identifiesControllerService":false,"sensitive":false,"resourceDefinition":{"cardinality":"MULTIPLE","resourceTypes":["DIRECTORY","FILE","URL"]}},"dbcp-max-idle-conns":{"name":"dbcp-max-idle-conns","displayName":"Max Idle Connections","identifiesControllerService":false,"sensitive":false},"Password":{"name":"Password","displayName":"Password","identifiesControllerService":false,"sensitive":true}},"controllerServiceApis":[{"type":"org.apache.nifi.dbcp.DBCPService","bundle":{"group":"org.apache.nifi","artifact":"nifi-standard-services-api-nar","version":"1.17.0"}}],"scheduledState":"DISABLED","bulletinLevel":"WARN","componentType":"CONTROLLER_SERVICE","groupIdentifier":"50e89c1a-0aad-32ee-96ce-08f118f282ce"}],"variables":{},"defaultFlowFileExpiration":"0 sec","defaultBackPressureObjectThreshold":10000,"defaultBackPressureDataSizeThreshold":"1 GB","componentType":"PROCESS_GROUP","flowFileConcurrency":"UNBOUNDED","flowFileOutboundPolicy":"STREAM_WHEN_AVAILABLE"},"externalControllerServices":{},"parameterContexts":{},"flowEncodingVersion":"1.0"}